MANIFEST.in
README.rst
setup.py
django_celery_addon/__init__.py
django_celery_addon/addon_config.py
django_celery_addon/celery.py
django_celery_addon/cli.py
django_celery_addon.egg-info/PKG-INFO
django_celery_addon.egg-info/SOURCES.txt
django_celery_addon.egg-info/dependency_links.txt
django_celery_addon.egg-info/entry_points.txt
django_celery_addon.egg-info/not-zip-safe
django_celery_addon.egg-info/requires.txt
django_celery_addon.egg-info/top_level.txt