Metadata-Version: 1.1
Name: django-celery-addon
Version: 4.1.0.2
Summary: An opinionated Celery setup bundled as an Django Addon..
Home-page: https://github.com/django-addons/django-celery-addon
Author: Divio AG
Author-email: info@divio.ch
License: UNKNOWN
Platform: UNKNOWN
Classifier: Development Status :: 2 - Pre-Alpha
Classifier: Programming Language :: Python :: 3.6
Classifier: Framework :: Django :: 2.0
